quadx88/__init__.py
quadx88/copter.py
quadx88-0.3.1.dist-info/METADATA
quadx88-0.3.1.dist-info/WHEEL
quadx88-0.3.1.dist-info/top_level.txt
quadx88-0.3.1.dist-info/RECORD
