Metadata-Version: 2.1
Name: quadx88
Version: 0.3.1
Summary: Configurable dynamical model of quadcopter
Home-page: https://github.com/alphaville/quadx88
Author: ['Ruairi Moran', 'Pantelis Sopasakis']
Author-email: p.sopasakis@gmail.com
License: MIT License
Keywords: quadcopter
Classifier: Programming Language :: Python
Classifier: Intended Audience :: Science/Research
Classifier: Topic :: Software Development :: Libraries
Classifier: Topic :: Scientific/Engineering
Requires-Dist: numpy
Requires-Dist: scipy
Requires-Dist: pyquaternion
Requires-Dist: control
